freshgui.py
freshgui-0.1.dist-info/METADATA
freshgui-0.1.dist-info/WHEEL
freshgui-0.1.dist-info/RECORD
